my_math/__init__.py
my_math/operations.py
maheshseeda_mymath-0.1.dist-info/METADATA
maheshseeda_mymath-0.1.dist-info/WHEEL
maheshseeda_mymath-0.1.dist-info/top_level.txt
maheshseeda_mymath-0.1.dist-info/RECORD
