Metadata-Version: 2.4
Name: maheshseeda-mymath
Version: 0.1
Summary: Simple math library with add and multiply functions
Author: mahesh
Dynamic: author
Dynamic: summary
